docs/_static/data_drift_detection.png
docs/_static/eurybia-fond-clair.png
docs/_static/lifecycle_ml_models.png
docs/_static/maif.png
docs/assets/css/style.css
docs/assets/images/contributing/eurybia-clone.png
docs/assets/images/contributing/eurybia-compare-pr.png
docs/assets/images/contributing/eurybia-create-pr.png
docs/assets/images/contributing/eurybia-fork.png
docs/assets/images/contributing/eurybia-pr-branch.png
docs/assets/images/contributing/eurybia-pr-description.png
docs/assets/images/contributing/eurybia-pr.png
docs/source/conf.py
docs/source/installation-instructions/plotly.png
docs/source/installation-instructions/widget.png
eurybia/__init__.py
eurybia/assets/__init__.py
eurybia/assets/local-report-base.css
eurybia/assets/local-report-base.js
eurybia/assets/logo_eurybia_dp.png
eurybia/core/__init__.py
eurybia/core/smartdrift.py
eurybia/core/smartplotter.py
eurybia/data/US_Accidents_extract.csv
eurybia/data/data_loader.py
eurybia/data/house_prices_dataset.csv
eurybia/data/house_prices_labels.json
eurybia/data/project_info_car_accident.yml
eurybia/data/project_info_house_price.yml
eurybia/data/project_info_titanic.yml
eurybia/data/titanic_altered.csv
eurybia/data/titanic_original.csv
eurybia/data/titanicdata.csv
eurybia/report/__init__.py
eurybia/report/common.py
eurybia/report/data_analysis.py
eurybia/report/generation.py
eurybia/report/project_report.py
eurybia/report/properties.py
eurybia/style/colors.json
eurybia/style/style_utils.py
eurybia/utils/io.py
eurybia/utils/model_drift.py
eurybia/utils/statistical_tests.py
eurybia/utils/utils.py
tests/__init__.py
tests/data/AUC_Histo.csv
tests/data/project_info.yml
tests/integration_tests/test_integration_smartdrift.py
tests/integration_tests/test_report_generation.py
tests/unit_tests/__init__.py
tests/unit_tests/core/__init__.py
tests/unit_tests/core/test_smartdrift.py
tests/unit_tests/core/test_smartplotter.py
tests/unit_tests/report/test_common.py
tests/unit_tests/report/test_data_analysis.py
eurybia-1.3.3.dist-info/LICENSE
eurybia-1.3.3.dist-info/METADATA
eurybia-1.3.3.dist-info/WHEEL
eurybia-1.3.3.dist-info/top_level.txt
eurybia-1.3.3.dist-info/RECORD
