Metadata-Version: 2.1
Name: eurybia
Version: 1.3.3
Summary: Eurybia monitor model drift over time and securize model deployment with data validation
Author: Nicolas Roux, Johann Martin
Author-email: Thomas Bouché <thomas.bouche@maif.fr>
License: Apache Software License 2.0
Classifier: Programming Language :: Python :: 3
Classifier: Programming Language :: Python :: 3.9
Classifier: Programming Language :: Python :: 3.10
Classifier: Programming Language :: Python :: 3.11
Classifier: Programming Language :: Python :: 3.12
Classifier: License :: OSI Approved :: Apache Software License
Classifier: Operating System :: OS Independent
Requires-Python: >=3.9
License-File: LICENSE
Requires-Dist: pandas>=2
Requires-Dist: catboost>=1.0.1
Requires-Dist: panel>=1.4.1
Requires-Dist: jinja2>=2.11.0
Requires-Dist: scipy>=1.4.0
Requires-Dist: seaborn>=0.10.1
Requires-Dist: shapash>=2.0.0
Requires-Dist: plotly
Provides-Extra: all
Requires-Dist: eurybia[dev,mypy,ruff,test]; extra == "all"
Provides-Extra: dev
Requires-Dist: pre-commit; extra == "dev"
Requires-Dist: mypy; extra == "dev"
Requires-Dist: ruff; extra == "dev"
Provides-Extra: mypy
Requires-Dist: mypy; extra == "mypy"
Provides-Extra: ruff
Requires-Dist: ruff; extra == "ruff"
Provides-Extra: test
Requires-Dist: pytest; extra == "test"
Requires-Dist: pytest-cov; extra == "test"
